cellmaps_utils/__init__.py
cellmaps_utils/apms_readme.txt
cellmaps_utils/apmstool.py
cellmaps_utils/basecmdtool.py
cellmaps_utils/cellmaps_utilscmd.py
cellmaps_utils/challenge.py
cellmaps_utils/constants.py
cellmaps_utils/crispr_readme.txt
cellmaps_utils/crisprtool.py
cellmaps_utils/ddotconverter.py
cellmaps_utils/exceptions.py
cellmaps_utils/hcx_utils.py
cellmaps_utils/hidefconverter.py
cellmaps_utils/hierdiff.py
cellmaps_utils/ifimage_readme.txt
cellmaps_utils/iftool.py
cellmaps_utils/logutils.py
cellmaps_utils/music_utils.py
cellmaps_utils/ndexupload.py
cellmaps_utils/provenance.py
cellmaps_utils/statsgenerator.py
cellmaps_utils/tabletool.py
cellmaps_utils-0.9.0.data/scripts/cellmaps_utilscmd.py
cellmaps_utils-0.9.0.dist-info/AUTHORS.rst
cellmaps_utils-0.9.0.dist-info/LICENSE
cellmaps_utils-0.9.0.dist-info/METADATA
cellmaps_utils-0.9.0.dist-info/WHEEL
cellmaps_utils-0.9.0.dist-info/top_level.txt
cellmaps_utils-0.9.0.dist-info/RECORD
