Metadata-Version: 2.1
Name: cellmaps_utils
Version: 0.9.0
Summary: Contains utilities needed by Cell Maps tools
Home-page: https://github.com/idekerlab/cellmaps_utils
Author: Cell Maps team
Author-email: tools@cm4ai.org
License: MIT license
Keywords: cellmaps_utils
Classifier: Development Status :: 2 - Pre-Alpha
Classifier: Intended Audience :: Developers
Classifier: License :: OSI Approved :: MIT License
Classifier: Natural Language :: English
Classifier: Programming Language :: Python :: 3.8
Classifier: Programming Language :: Python :: 3.9
Classifier: Programming Language :: Python :: 3.10
Classifier: Programming Language :: Python :: 3.11
License-File: LICENSE
License-File: AUTHORS.rst
Requires-Dist: fairscape-cli ==1.0.2
Requires-Dist: ndex2 <4.0.0,>=3.8.0
Requires-Dist: scipy <1.13.0,>=1.10.1
Requires-Dist: scikit-learn <1.4.0,>=0.19.0
Requires-Dist: pandas <3.0.0,>=2.0.0
Requires-Dist: numpy <2.0.0,>=1.24.4
Requires-Dist: dill <0.4.0,>=0.3.8
Requires-Dist: tqdm <5.0.0,>=4.66.6
Requires-Dist: requests <3.0.0,>=2.31.0
